README.rst
setup.py
redisq/__init__.py
redisq/client.py
redisq/task.py
redisq_py.egg-info/PKG-INFO
redisq_py.egg-info/SOURCES.txt
redisq_py.egg-info/dependency_links.txt
redisq_py.egg-info/requires.txt
redisq_py.egg-info/top_level.txt
tests/__init__.py
tests/tests.py