Metadata-Version: 1.1
Name: redisq-py
Version: 1.0.0
Summary: A python client for redisq (Fast message processing queue backed up by redis and nodejs.)
Home-page: https://github.com/joshuakarjala/redisq-py/
Author: Joshua Karjala-Svenden
Author-email: joshua@fluxuries.com
License: MIT
Platform: any
Classifier: Development Status :: 5 - Production/Stable
Classifier: Intended Audience :: Developers
Classifier: License :: OSI Approved :: MIT License
Classifier: Operating System :: OS Independent
Classifier: Programming Language :: Python
Classifier: Topic :: Software Development :: Libraries :: Python Modules
